{"assets/logos/adidas.jpg":["assets/logos/adidas.jpg"],"assets/logos/amazon.jpg":["assets/logos/amazon.jpg"],"assets/logos/apple.jpg":["assets/logos/apple.jpg"],"assets/logos/audi.jpg":["assets/logos/audi.jpg"],"assets/logos/bently.jpg":["assets/logos/bently.jpg"],"assets/logos/benz.jpg":["assets/logos/benz.jpg"],"assets/logos/bmw.jpg":["assets/logos/bmw.jpg"],"assets/logos/chanel.jpg":["assets/logos/chanel.jpg"],"assets/logos/cisco.jpg":["assets/logos/cisco.jpg"],"assets/logos/cocacola.jpg":["assets/logos/cocacola.jpg"],"assets/logos/dell.jpg":["assets/logos/dell.jpg"],"assets/logos/disney.jpg":["assets/logos/disney.jpg"],"assets/logos/dominos.jpg":["assets/logos/dominos.jpg"],"assets/logos/facebook.jpg":["assets/logos/facebook.jpg"],"assets/logos/ferrari.jpg":["assets/logos/ferrari.jpg"],"assets/logos/google.jpg":["assets/logos/google.jpg"],"assets/logos/gucci.jpg":["assets/logos/gucci.jpg"],"assets/logos/h&m.jpg":["assets/logos/h&m.jpg"],"assets/logos/hp.jpg":["assets/logos/hp.jpg"],"assets/logos/huawei.jpg":["assets/logos/huawei.jpg"],"assets/logos/hyundai.jpg":["assets/logos/hyundai.jpg"],"assets/logos/ibm.jpg":["assets/logos/ibm.jpg"],"assets/logos/instagram.jpg":["assets/logos/instagram.jpg"],"assets/logos/intel.jpg":["assets/logos/intel.jpg"],"assets/logos/kfc.jpg":["assets/logos/kfc.jpg"],"assets/logos/lacoste.jpg":["assets/logos/lacoste.jpg"],"assets/logos/levis.jpg":["assets/logos/levis.jpg"],"assets/logos/lg.jpg":["assets/logos/lg.jpg"],"assets/logos/linkedin.jpg":["assets/logos/linkedin.jpg"],"assets/logos/louisvuition.jpg":["assets/logos/louisvuition.jpg"],"assets/logos/mastercard.jpg":["assets/logos/mastercard.jpg"],"assets/logos/meesho.jpg":["assets/logos/meesho.jpg"],"assets/logos/microsoft.jpg":["assets/logos/microsoft.jpg"],"assets/logos/myntra.jpg":["assets/logos/myntra.jpg"],"assets/logos/nasa.jpg":["assets/logos/nasa.jpg"],"assets/logos/netflix.jpg":["assets/logos/netflix.jpg"],"assets/logos/nike.jpg":["assets/logos/nike.jpg"],"assets/logos/nivea.jpg":["assets/logos/nivea.jpg"],"assets/logos/oppo.jpg":["assets/logos/oppo.jpg"],"assets/logos/oracle.jpg":["assets/logos/oracle.jpg"],"assets/logos/paypal.jpg":["assets/logos/paypal.jpg"],"assets/logos/pepsi.jpg":["assets/logos/pepsi.jpg"],"assets/logos/puma.jpg":["assets/logos/puma.jpg"],"assets/logos/rolex.jpg":["assets/logos/rolex.jpg"],"assets/logos/salesforce.jpg":["assets/logos/salesforce.jpg"],"assets/logos/samsung.jpg":["assets/logos/samsung.jpg"],"assets/logos/sony.jpg":["assets/logos/sony.jpg"],"assets/logos/spotify.jpg":["assets/logos/spotify.jpg"],"assets/logos/starbucks.jpg":["assets/logos/starbucks.jpg"],"assets/logos/subway.jpg":["assets/logos/subway.jpg"],"assets/logos/tesla.jpg":["assets/logos/tesla.jpg"],"assets/logos/toyota.jpg":["assets/logos/toyota.jpg"],"assets/logos/uber.jpg":["assets/logos/uber.jpg"],"assets/logos/uniqlo.jpg":["assets/logos/uniqlo.jpg"],"assets/logos/visa.jpg":["assets/logos/visa.jpg"],"assets/logos/vivo.jpg":["assets/logos/vivo.jpg"],"assets/logos/warnerbros.jpg":["assets/logos/warnerbros.jpg"],"assets/logos/whatsapp.jpg":["assets/logos/whatsapp.jpg"],"assets/logos/youtube.jpg":["assets/logos/youtube.jpg"],"assets/logos/zara.jpg":["assets/logos/zara.jpg"],"assets/logos/zoom.jpg":["assets/logos/zoom.jpg"],"packages/cupertino_icons/assets/CupertinoIcons.ttf":["packages/cupertino_icons/assets/CupertinoIcons.ttf"]}